nipyproto.py
nipyproto-1.1.1.dist-info/METADATA
nipyproto-1.1.1.dist-info/WHEEL
nipyproto-1.1.1.dist-info/entry_points.txt
nipyproto-1.1.1.dist-info/top_level.txt
nipyproto-1.1.1.dist-info/RECORD
